mabs/__init__.py
mabs/hello.py
magnon-0.0.0.dist-info/METADATA
magnon-0.0.0.dist-info/WHEEL
magnon-0.0.0.dist-info/top_level.txt
magnon-0.0.0.dist-info/RECORD
