Metadata-Version: 2.4
Name: magnon
Version: 0.0.0
Summary: Magnon is coming soon.
Author-email: Alex Moorhouse <aem228@cam.ac.uk>
Requires-Python: >=3.12
Requires-Dist: numpy>=2.0
Requires-Dist: matplotlib>=3.9.2
Requires-Dist: spglib>=2.5
Requires-Dist: ase>=3.23
Requires-Dist: pytest>=7
